todo.txt_pylib-0.1.post1.dist-info/DESCRIPTION.rst
todo.txt_pylib-0.1.post1.dist-info/METADATA
todo.txt_pylib-0.1.post1.dist-info/RECORD
todo.txt_pylib-0.1.post1.dist-info/WHEEL
todo.txt_pylib-0.1.post1.dist-info/metadata.json
todo.txt_pylib-0.1.post1.dist-info/top_level.txt
todotxt/__init__.py
