Metadata-Version: 2.0
Name: todo.txt-pylib
Version: 0.1.post1
Summary: A pythonic interface to Gina Trapani's todo.txt-format for Python 3.
Home-page: https://github.com/funkyfuture/todo.txt-pylib
Author: Frank Sachsenheim
Author-email: funkyfuture@riseup.net
License: Copyright (c) 2016, Frank Sachsenheim
